coda/CODA.txt
coda/__init__.py
coda/__init__.py.bak
coda/test.py
coda/test.py.bak
coda/test_readme.py
coda/__pycache__/__init__.cpython-36.opt-1.pyc
coda/__pycache__/__init__.cpython-36.pyc
coda/__pycache__/__init__.cpython-37.pyc
coda/__pycache__/__init__.cpython-38.pyc
coda/__pycache__/__init__.cpython-39.pyc
coda/__pycache__/test.cpython-38.pyc
coda/__pycache__/test.cpython-39.pyc
febelfin_coda.egg-info/PKG-INFO
febelfin_coda.egg-info/SOURCES.txt
febelfin_coda.egg-info/dependency_links.txt
febelfin_coda.egg-info/top_level.txt
febelfin_coda-0.3.0.dist-info/METADATA
febelfin_coda-0.3.0.dist-info/WHEEL
febelfin_coda-0.3.0.dist-info/top_level.txt
febelfin_coda-0.3.0.dist-info/RECORD
