Metadata-Version: 2.1
Name: febelfin-coda
Version: 0.3.0
Summary: A module to parse CODA files
Home-page: https://pypi.org/project/febelfin-coda/
Download-URL: https://downloads.tryton.org/coda/
Author: Tryton
Author-email: foundation@tryton.org
License: BSD
Project-URL: Bug Tracker, https://bugs.tryton.org/coda
Project-URL: Forum, https://discuss.tryton.org/tags/coda
Project-URL: Source Code, https://code.tryton.org/coda
Keywords: CODA parser
Classifier: Intended Audience :: Developers
Classifier: License :: OSI Approved :: BSD License
Classifier: Operating System :: OS Independent
Classifier: Programming Language :: Python :: 3
Classifier: Programming Language :: Python :: 3.5
Classifier: Programming Language :: Python :: 3.6
Classifier: Programming Language :: Python :: 3.7
Classifier: Programming Language :: Python :: 3.8
Classifier: Programming Language :: Python :: 3.9
Classifier: Programming Language :: Python :: 3.10
Classifier: Programming Language :: Python :: 3.11
Classifier: Programming Language :: Python :: 3.12
Classifier: Topic :: Office/Business
Classifier: Topic :: Software Development :: Libraries
Classifier: Topic :: Utilities
Requires-Python: >=3.5
